[
    {
        "timestamp": "2025-06-27 10:00:32",
        "user": "1052",
        "action": "update_regis_setting",
        "data": {
            "ม.1": {
                "regis_start": "2024-06-10 08:00:00",
                "regis_end": "2024-06-15 23:59:00"
            },
            "ม.2": {
                "regis_start": "2025-05-14 16:00:00",
                "regis_end": "2025-06-20 23:59:00"
            },
            "ม.3": {
                "regis_start": "2024-06-14 08:00:00",
                "regis_end": "2024-06-19 23:59:00"
            },
            "ม.4": {
                "regis_start": "2025-05-21 16:00:00",
                "regis_end": "2025-06-20 23:59:00"
            },
            "ม.5": {
                "regis_start": "2025-05-21 16:00:00",
                "regis_end": "2025-06-20 23:59:00"
            },
            "ม.6": {
                "regis_start": "2025-05-21 16:00:00",
                "regis_end": "2025-06-30 23:59:00"
            }
        }
    },
    {
        "timestamp": "2025-06-27 10:08:26",
        "user": "1052",
        "action": "update_regis_setting",
        "data": {
            "ม.1": {
                "regis_start": "2024-06-10 08:00:00",
                "regis_end": "2024-06-15 23:59:00"
            },
            "ม.2": {
                "regis_start": "2025-05-14 16:00:00",
                "regis_end": "2025-06-20 23:59:00"
            },
            "ม.3": {
                "regis_start": "2024-06-14 08:00:00",
                "regis_end": "2024-06-19 23:59:00"
            },
            "ม.4": {
                "regis_start": "2025-05-21 16:00:00",
                "regis_end": "2025-06-20 23:59:00"
            },
            "ม.5": {
                "regis_start": "2025-05-21 16:00:00",
                "regis_end": "2025-06-30 23:59:00"
            },
            "ม.6": {
                "regis_start": "2025-05-21 16:00:00",
                "regis_end": "2025-06-30 23:59:00"
            }
        }
    }
]